{
  "actions": [
    {
      "type": "alterTable",
      "alterTable": {
        "name": "location",
        "schema": "public",
        "addColumns": [
          {
            "name": "address",
            "columnType": 0,
            "isNullable": true,
            "dartType": "String?"
          },
          {
            "name": "googleMapsUrl",
            "columnType": 0,
            "isNullable": true,
            "dartType": "String?"
          }
        ],
        "deleteColumns": [],
        "modifyColumns": [],
        "addIndexes": [],
        "deleteIndexes": [],
        "addForeignKeys": [],
        "deleteForeignKeys": [],
        "warnings": []
      }
    }
  ],
  "warnings": [],
  "migrationApiVersion": 1
}